django_okta_client-1.2.3.dist-info/licenses/LICENSE
okta_client/__init__.py
okta_client/__main__.py
okta_client/api_client.py
okta_client/apps.py
okta_client/auth_backends.py
okta_client/exceptions.py
okta_client/groups.py
okta_client/managers.py
okta_client/mixins.py
okta_client/models.py
okta_client/settings.py
okta_client/tests.py
okta_client/urls.py
okta_client/utils.py
okta_client/views.py
okta_client/admin/__init__.py
okta_client/admin/options.py
okta_client/management/__init__.py
okta_client/management/commands/__init__.py
okta_client/management/commands/rewrite_okta_event_signals.py
okta_client/management/commands/update_users_from_okta.py
okta_client/migrations/0001_initial.py
okta_client/migrations/0002_alter_oktauser_options_alter_oktauser_managers_and_more.py
okta_client/migrations/0003_oktauser_last_refresh_timestamp_and_more.py
okta_client/migrations/__init__.py
okta_client/signals/__init__.py
okta_client/signals/events.py
okta_client/signals/groups.py
okta_client/signals/handlers.py
okta_client/signals/local_handlers.py
okta_client/templates/okta-client/index.html
okta_client/templates/okta-client/signals_events.py-template
django_okta_client-1.2.3.dist-info/METADATA
django_okta_client-1.2.3.dist-info/WHEEL
django_okta_client-1.2.3.dist-info/top_level.txt
django_okta_client-1.2.3.dist-info/RECORD
